setup.cfg
setup.py
pymcts/__init__.py
pymcts/mc_tree.py
pymcts/tree.py
pymcts/uct.py
pymcts.egg-info/PKG-INFO
pymcts.egg-info/SOURCES.txt
pymcts.egg-info/dependency_links.txt
pymcts.egg-info/requires.txt
pymcts.egg-info/top_level.txt
pymcts.egg-info/zip-safe
pymcts/game/__init__.py
pymcts/game/tic_tac_toe.py
pymcts/game/trivial.py
tests/__init__.py
tests/mc_tree_test.py
tests/tree_test.py
tests/uct_test.py