Metadata-Version: 1.1
Name: pymcts
Version: 0.1
Summary: Python implementation of Monte Carlo Tree Search (MCTS)
Home-page: https://github.com/smallnamespace/pymcts
Author: smallnamespace
Author-email: smallnamespace@gmail.com
License: ASL v2
Download-URL: https://github.com/smallnamespace/pymcts/tarball/master
Platform: UNKNOWN
Classifier: Development Status :: 2 - Pre-Alpha
Classifier: Intended Audience :: Developers
Classifier: License :: OSI Approved :: Apache Software License
Classifier: Programming Language :: Python
Classifier: Programming Language :: Python :: 3
Classifier: Programming Language :: Python :: 3.5
Classifier: Topic :: Games/Entertainment :: Turn Based Strategy
